{"isMarkdown":true,"isTranslated":false,"isActive":true,"flaws":{},"title":"GPURenderPassEncoder","mdn_url":"/en-US/docs/Web/API/GPURenderPassEncoder","locale":"en-US","native":"English (US)","browserCompat":["api.GPURenderPassEncoder"],"baseline":{"baseline":false,"support":{"chrome":"113","edge":"113"}},"summary":"The GPURenderPassEncoder interface of the WebGPU API encodes commands related to controlling the vertex and fragment shader stages, as issued by a GPURenderPipeline. It forms part of the overall encoding activity of a GPUCommandEncoder.","popularity":0.0007,"modified":null,"other_translations":[],"pageType":"web-api-interface","source":{"folder":"en-us/web/api/gpurenderpassencoder","github_url":"https://github.com/mdn/content/blob/main/files/en-us/web/api/gpurenderpassencoder/index.md","last_commit_url":"https://github.com/mdn/content/commit/null","filename":"index.md"},"short_title":"GPURenderPassEncoder","parents":[{"uri":"/en-US/docs/Web","title":"References"},{"uri":"/en-US/docs/Web/API","title":"Web APIs"},{"uri":"/en-US/docs/Web/API/GPURenderPassEncoder","title":"GPURenderPassEncoder"}],"pageTitle":"GPURenderPassEncoder - Web APIs | MDN","noIndexing":false,"hash":"b165a31ae7d23b16f88846972ea828b70f93004875428c22669a277402f93c41"}