{"isMarkdown":true,"isTranslated":false,"isActive":true,"flaws":{},"title":"Geometry interfaces","mdn_url":"/en-US/docs/Web/API/Geometry_interfaces","locale":"en-US","native":"English (US)","browserCompat":["api.DOMMatrix","api.DOMMatrixReadOnly","api.DOMPoint","api.DOMPointReadOnly","api.DOMQuad","api.DOMRect","api.DOMRectReadOnly"],"summary":"Geometry interfaces is a CSS module that provides interfaces for working with 3D and 2D graphics — in particular, for working with points, rectangles, quadrilaterals and transformation matrices (for operations that translate/move, scale, rotate, skew/shear/slant, and flip graphics, as well as for multiplying/chaining and inverting/undoing those operations).","popularity":0.0018,"modified":null,"other_translations":[],"pageType":"web-api-overview","source":{"folder":"en-us/web/api/geometry_interfaces","github_url":"https://github.com/mdn/content/blob/main/files/en-us/web/api/geometry_interfaces/index.md","last_commit_url":"https://github.com/mdn/content/commit/null","filename":"index.md"},"short_title":"Geometry interfaces","parents":[{"uri":"/en-US/docs/Web","title":"References"},{"uri":"/en-US/docs/Web/API","title":"Web APIs"},{"uri":"/en-US/docs/Web/API/Geometry_interfaces","title":"Geometry interfaces"}],"pageTitle":"Geometry interfaces - Web APIs | MDN","noIndexing":false,"hash":"263285dbf73f72558de34ef82506bcc40efcd44d1747c6042fac6b91c99d7120"}