{"isMarkdown":true,"isTranslated":false,"isActive":true,"flaws":{},"title":"CSSStyleRule","mdn_url":"/en-US/docs/Web/API/CSSStyleRule","locale":"en-US","native":"English (US)","browserCompat":["api.CSSStyleRule"],"baseline":{"baseline":"high","baseline_high_date":"2018-03-30","baseline_low_date":"2015-09-30","support":{"chrome":"28","chrome_android":"28","edge":"12","firefox":"22","firefox_android":"22","safari":"9","safari_ios":"9"}},"summary":"The CSSStyleRule interface represents a single CSS style rule.","popularity":0.0022,"modified":"2020-10-15T21:12:02.772Z","other_translations":[],"pageType":"web-api-interface","source":{"folder":"en-us/web/api/cssstylerule","github_url":"https://github.com/mdn/content/blob/main/files/en-us/web/api/cssstylerule/index.md","last_commit_url":"https://github.com/mdn/content/commit/null","filename":"index.md"},"short_title":"CSSStyleRule","parents":[{"uri":"/en-US/docs/Web","title":"References"},{"uri":"/en-US/docs/Web/API","title":"Web APIs"},{"uri":"/en-US/docs/Web/API/CSSStyleRule","title":"CSSStyleRule"}],"pageTitle":"CSSStyleRule - Web APIs | MDN","noIndexing":false,"hash":"b4c4c500825e06fe507d1350c2e14c388f1df582080543e1351576b035604044"}