{"doc":{"isMarkdown":true,"isTranslated":false,"isActive":true,"flaws":{},"title":"GPURenderBundle","mdn_url":"/en-US/docs/Web/API/GPURenderBundle","locale":"en-US","native":"English (US)","browserCompat":["api.GPURenderBundle"],"baseline":{"baseline":false,"support":{"chrome":"113","edge":"113"}},"sidebarHTML":"<ol><li class=\"section\"><a href=\"/en-US/docs/Web/API/WebGPU_API\">WebGPU API</a><abbr class=\"icon icon-experimental\" title=\"Experimental. Expect behavior to change in the future.\">\n    <span class=\"visually-hidden\">Experimental</span>\n</abbr></li><li class=\"section\"><em><a href=\"/en-US/docs/Web/API/GPURenderBundle\" aria-current=\"page\"><code>GPURenderBundle</code></a><abbr class=\"icon icon-experimental\" title=\"Experimental. Expect behavior to change in the future.\">\n    <span class=\"visually-hidden\">Experimental</span>\n</abbr></em></li><li class=\"toggle\"><details open=\"\"><summary>Instance properties</summary><ol><li><a href=\"/en-US/docs/Web/API/GPURenderBundle/label\"><code>label</code></a><abbr class=\"icon icon-experimental\" title=\"Experimental. Expect behavior to change in the future.\">\n    <span class=\"visually-hidden\">Experimental</span>\n</abbr></li></ol></details></li><li class=\"toggle\"><details open=\"\"><summary>Related pages for WebGPU API</summary><ol><li><a href=\"/en-US/docs/Web/API/GPU\"><code>GPU</code></a><abbr class=\"icon icon-experimental\" title=\"Experimental. Expect behavior to change in the future.\">\n    <span class=\"visually-hidden\">Experimental</span>\n</abbr></li><li><a href=\"/en-US/docs/Web/API/GPUAdapter\"><code>GPUAdapter</code></a><abbr class=\"icon icon-experimental\" title=\"Experimental. Expect behavior to change in the future.\">\n    <span class=\"visually-hidden\">Experimental</span>\n</abbr></li><li><a href=\"/en-US/docs/Web/API/GPUAdapterInfo\"><code>GPUAdapterInfo</code></a><abbr class=\"icon icon-experimental\" title=\"Experimental. Expect behavior to change in the future.\">\n    <span class=\"visually-hidden\">Experimental</span>\n</abbr></li><li><a href=\"/en-US/docs/Web/API/GPUBindGroup\"><code>GPUBindGroup</code></a><abbr class=\"icon icon-experimental\" title=\"Experimental. Expect behavior to change in the future.\">\n    <span class=\"visually-hidden\">Experimental</span>\n</abbr></li><li><a href=\"/en-US/docs/Web/API/GPUBindGroupLayout\"><code>GPUBindGroupLayout</code></a><abbr class=\"icon icon-experimental\" title=\"Experimental. Expect behavior to change in the future.\">\n    <span class=\"visually-hidden\">Experimental</span>\n</abbr></li><li><a href=\"/en-US/docs/Web/API/GPUBuffer\"><code>GPUBuffer</code></a><abbr class=\"icon icon-experimental\" title=\"Experimental. Expect behavior to change in the future.\">\n    <span class=\"visually-hidden\">Experimental</span>\n</abbr></li><li><a href=\"/en-US/docs/Web/API/GPUCanvasContext\"><code>GPUCanvasContext</code></a><abbr class=\"icon icon-experimental\" title=\"Experimental. Expect behavior to change in the future.\">\n    <span class=\"visually-hidden\">Experimental</span>\n</abbr></li><li><a href=\"/en-US/docs/Web/API/GPUCommandBuffer\"><code>GPUCommandBuffer</code></a><abbr class=\"icon icon-experimental\" title=\"Experimental. Expect behavior to change in the future.\">\n    <span class=\"visually-hidden\">Experimental</span>\n</abbr></li><li><a href=\"/en-US/docs/Web/API/GPUCommandEncoder\"><code>GPUCommandEncoder</code></a><abbr class=\"icon icon-experimental\" title=\"Experimental. Expect behavior to change in the future.\">\n    <span class=\"visually-hidden\">Experimental</span>\n</abbr></li><li><a href=\"/en-US/docs/Web/API/GPUCompilationInfo\"><code>GPUCompilationInfo</code></a><abbr class=\"icon icon-experimental\" title=\"Experimental. Expect behavior to change in the future.\">\n    <span class=\"visually-hidden\">Experimental</span>\n</abbr></li><li><a href=\"/en-US/docs/Web/API/GPUCompilationMessage\"><code>GPUCompilationMessage</code></a><abbr class=\"icon icon-experimental\" title=\"Experimental. Expect behavior to change in the future.\">\n    <span class=\"visually-hidden\">Experimental</span>\n</abbr></li><li><a href=\"/en-US/docs/Web/API/GPUComputePassEncoder\"><code>GPUComputePassEncoder</code></a><abbr class=\"icon icon-experimental\" title=\"Experimental. Expect behavior to change in the future.\">\n    <span class=\"visually-hidden\">Experimental</span>\n</abbr></li><li><a href=\"/en-US/docs/Web/API/GPUComputePipeline\"><code>GPUComputePipeline</code></a><abbr class=\"icon icon-experimental\" title=\"Experimental. Expect behavior to change in the future.\">\n    <span class=\"visually-hidden\">Experimental</span>\n</abbr></li><li><a href=\"/en-US/docs/Web/API/GPUDevice\"><code>GPUDevice</code></a><abbr class=\"icon icon-experimental\" title=\"Experimental. Expect behavior to change in the future.\">\n    <span class=\"visually-hidden\">Experimental</span>\n</abbr></li><li><a href=\"/en-US/docs/Web/API/GPUDeviceLostInfo\"><code>GPUDeviceLostInfo</code></a><abbr class=\"icon icon-experimental\" title=\"Experimental. Expect behavior to change in the future.\">\n    <span class=\"visually-hidden\">Experimental</span>\n</abbr></li><li><a href=\"/en-US/docs/Web/API/GPUError\"><code>GPUError</code></a><abbr class=\"icon icon-experimental\" title=\"Experimental. Expect behavior to change in the future.\">\n    <span class=\"visually-hidden\">Experimental</span>\n</abbr></li><li><a href=\"/en-US/docs/Web/API/GPUExternalTexture\"><code>GPUExternalTexture</code></a><abbr class=\"icon icon-experimental\" title=\"Experimental. Expect behavior to change in the future.\">\n    <span class=\"visually-hidden\">Experimental</span>\n</abbr></li><li><a href=\"/en-US/docs/Web/API/GPUInternalError\"><code>GPUInternalError</code></a><abbr class=\"icon icon-experimental\" title=\"Experimental. Expect behavior to change in the future.\">\n    <span class=\"visually-hidden\">Experimental</span>\n</abbr></li><li><a href=\"/en-US/docs/Web/API/GPUOutOfMemoryError\"><code>GPUOutOfMemoryError</code></a><abbr class=\"icon icon-experimental\" title=\"Experimental. Expect behavior to change in the future.\">\n    <span class=\"visually-hidden\">Experimental</span>\n</abbr></li><li><a href=\"/en-US/docs/Web/API/GPUPipelineError\"><code>GPUPipelineError</code></a><abbr class=\"icon icon-experimental\" title=\"Experimental. Expect behavior to change in the future.\">\n    <span class=\"visually-hidden\">Experimental</span>\n</abbr></li><li><a href=\"/en-US/docs/Web/API/GPUPipelineLayout\"><code>GPUPipelineLayout</code></a><abbr class=\"icon icon-experimental\" title=\"Experimental. Expect behavior to change in the future.\">\n    <span class=\"visually-hidden\">Experimental</span>\n</abbr></li><li><a href=\"/en-US/docs/Web/API/GPUQuerySet\"><code>GPUQuerySet</code></a><abbr class=\"icon icon-experimental\" title=\"Experimental. Expect behavior to change in the future.\">\n    <span class=\"visually-hidden\">Experimental</span>\n</abbr></li><li><a href=\"/en-US/docs/Web/API/GPUQueue\"><code>GPUQueue</code></a><abbr class=\"icon icon-experimental\" title=\"Experimental. Expect behavior to change in the future.\">\n    <span class=\"visually-hidden\">Experimental</span>\n</abbr></li><li><a href=\"/en-US/docs/Web/API/GPURenderBundleEncoder\"><code>GPURenderBundleEncoder</code></a><abbr class=\"icon icon-experimental\" title=\"Experimental. Expect behavior to change in the future.\">\n    <span class=\"visually-hidden\">Experimental</span>\n</abbr></li><li><a href=\"/en-US/docs/Web/API/GPURenderPassEncoder\"><code>GPURenderPassEncoder</code></a><abbr class=\"icon icon-experimental\" title=\"Experimental. Expect behavior to change in the future.\">\n    <span class=\"visually-hidden\">Experimental</span>\n</abbr></li><li><a href=\"/en-US/docs/Web/API/GPURenderPipeline\"><code>GPURenderPipeline</code></a><abbr class=\"icon icon-experimental\" title=\"Experimental. Expect behavior to change in the future.\">\n    <span class=\"visually-hidden\">Experimental</span>\n</abbr></li><li><a href=\"/en-US/docs/Web/API/GPUSampler\"><code>GPUSampler</code></a><abbr class=\"icon icon-experimental\" title=\"Experimental. Expect behavior to change in the future.\">\n    <span class=\"visually-hidden\">Experimental</span>\n</abbr></li><li><a href=\"/en-US/docs/Web/API/GPUShaderModule\"><code>GPUShaderModule</code></a><abbr class=\"icon icon-experimental\" title=\"Experimental. Expect behavior to change in the future.\">\n    <span class=\"visually-hidden\">Experimental</span>\n</abbr></li><li><a href=\"/en-US/docs/Web/API/GPUSupportedFeatures\"><code>GPUSupportedFeatures</code></a><abbr class=\"icon icon-experimental\" title=\"Experimental. Expect behavior to change in the future.\">\n    <span class=\"visually-hidden\">Experimental</span>\n</abbr></li><li><a href=\"/en-US/docs/Web/API/GPUSupportedLimits\"><code>GPUSupportedLimits</code></a><abbr class=\"icon icon-experimental\" title=\"Experimental. Expect behavior to change in the future.\">\n    <span class=\"visually-hidden\">Experimental</span>\n</abbr></li><li><a href=\"/en-US/docs/Web/API/GPUTexture\"><code>GPUTexture</code></a><abbr class=\"icon icon-experimental\" title=\"Experimental. Expect behavior to change in the future.\">\n    <span class=\"visually-hidden\">Experimental</span>\n</abbr></li><li><a href=\"/en-US/docs/Web/API/GPUTextureView\"><code>GPUTextureView</code></a><abbr class=\"icon icon-experimental\" title=\"Experimental. Expect behavior to change in the future.\">\n    <span class=\"visually-hidden\">Experimental</span>\n</abbr></li><li><a href=\"/en-US/docs/Web/API/GPUUncapturedErrorEvent\"><code>GPUUncapturedErrorEvent</code></a><abbr class=\"icon icon-experimental\" title=\"Experimental. Expect behavior to change in the future.\">\n    <span class=\"visually-hidden\">Experimental</span>\n</abbr></li><li><a href=\"/en-US/docs/Web/API/GPUValidationError\"><code>GPUValidationError</code></a><abbr class=\"icon icon-experimental\" title=\"Experimental. Expect behavior to change in the future.\">\n    <span class=\"visually-hidden\">Experimental</span>\n</abbr></li><li><a href=\"/en-US/docs/Web/API/HTMLCanvasElement/getContext\"><code>HTMLCanvasElement.getContext()</code></a></li><li><a href=\"/en-US/docs/Web/API/Navigator/gpu\"><code>Navigator.gpu</code></a><abbr class=\"icon icon-experimental\" title=\"Experimental. Expect behavior to change in the future.\">\n    <span class=\"visually-hidden\">Experimental</span>\n</abbr></li><li><a href=\"/en-US/docs/Web/API/WorkerNavigator/gpu\"><code>WorkerNavigator.gpu</code></a><abbr class=\"icon icon-experimental\" title=\"Experimental. Expect behavior to change in the future.\">\n    <span class=\"visually-hidden\">Experimental</span>\n</abbr></li></ol></details></li></ol>","sidebarMacro":"APIRef","body":[{"type":"prose","value":{"id":null,"title":null,"isH3":false,"content":"<div class=\"notecard experimental\"><p><strong>Experimental:</strong> <strong>This is an <a href=\"/en-US/docs/MDN/Writing_guidelines/Experimental_deprecated_obsolete#experimental\">experimental technology</a></strong><br>Check the <a href=\"#browser_compatibility\">Browser compatibility table</a> carefully before using this in production.</p></div><div class=\"notecard secure\"><p><strong>Secure context:</strong> This feature is available only in <a href=\"/en-US/docs/Web/Security/Secure_Contexts\">secure contexts</a> (HTTPS), in some or all <a href=\"#browser_compatibility\">supporting browsers</a>.</p></div><div class=\"notecard note\">\n  <p><strong>Note:</strong> This feature is available in <a href=\"/en-US/docs/Web/API/Web_Workers_API\">Web Workers</a>.</p>\n</div>\n<p>The <strong><code>GPURenderBundle</code></strong> interface of the <a href=\"/en-US/docs/Web/API/WebGPU_API\" title=\"WebGPU API\">WebGPU API</a> represents a container for pre-recorded bundles of commands.</p>\n<p>The command bundles are encoded using a <a href=\"/en-US/docs/Web/API/GPURenderBundleEncoder\"><code>GPURenderBundleEncoder</code></a>; once the desired commands have been encoded, they are recorded into a <code>GPURenderBundle</code> object instance using the <a href=\"/en-US/docs/Web/API/GPURenderBundleEncoder/finish\"><code>GPURenderBundleEncoder.finish()</code></a> method.</p>\n<p>These command bundles can then be reused across multiple render passes by passing the <code>GPURenderBundle</code> objects into <a href=\"/en-US/docs/Web/API/GPURenderPassEncoder/executeBundles\"><code>GPURenderPassEncoder.executeBundles()</code></a> calls. Reusing pre-recoded commands can significantly improve app performance in situations where JavaScript draw call overhead is a bottleneck. Render bundles are most effective in situations where a batch of objects will be drawn the same way across multiple views or frames, with the only differences being the buffer content being used (such as updated matrix uniforms).</p>\n<p>A good example is VR rendering. Recording the rendering as a render bundle and then tweaking the view matrix and replaying it for each eye is a more efficient way to issue draw calls for both renderings of the scene.</p>"}},{"type":"prose","value":{"id":"instance_properties","title":"Instance properties","isH3":false,"content":"<dl>\n  <dt id=\"label\"><a href=\"/en-US/docs/Web/API/GPURenderBundle/label\" title=\"label\"><code>label</code></a> <abbr class=\"icon icon-experimental\" title=\"Experimental. Expect behavior to change in the future.\">\n    <span class=\"visually-hidden\">Experimental</span>\n</abbr></dt>\n  <dd>\n    <p>A string providing a label that can be used to identify the object, for example in <a href=\"/en-US/docs/Web/API/GPUError\"><code>GPUError</code></a> messages or console warnings.</p>\n  </dd>\n</dl>"}},{"type":"prose","value":{"id":"examples","title":"Examples","isH3":false,"content":"<p>In the WebGPU Samples <a href=\"https://webgpu.github.io/webgpu-samples/samples/animometer/\" class=\"external\" target=\"_blank\">Animometer example</a>, a lot of like operations are done on many different objects simultaneously. A render bundle is encoded using the following function:</p>\n<div class=\"code-example\"><div class=\"example-header\"><span class=\"language-name\">js</span></div><pre class=\"brush: js notranslate\"><code>function recordRenderPass(\n  passEncoder: GPURenderBundleEncoder | GPURenderPassEncoder\n) {\n  if (settings.dynamicOffsets) {\n    passEncoder.setPipeline(dynamicPipeline);\n  } else {\n    passEncoder.setPipeline(pipeline);\n  }\n  passEncoder.setVertexBuffer(0, vertexBuffer);\n  passEncoder.setBindGroup(0, timeBindGroup);\n  const dynamicOffsets = [0];\n  for (let i = 0; i &lt; numTriangles; ++i) {\n    if (settings.dynamicOffsets) {\n      dynamicOffsets[0] = i * alignedUniformBytes;\n      passEncoder.setBindGroup(1, dynamicBindGroup, dynamicOffsets);\n    } else {\n      passEncoder.setBindGroup(1, bindGroups[i]);\n    }\n    passEncoder.draw(3, 1, 0, 0);\n  }\n}\n</code></pre></div>\n<p>Later on, a <a href=\"/en-US/docs/Web/API/GPURenderBundleEncoder\"><code>GPURenderBundleEncoder</code></a> is created, the function is invoked, and the render bundle is recorded using <a href=\"/en-US/docs/Web/API/GPURenderBundleEncoder/finish\"><code>GPURenderBundleEncoder.finish()</code></a>:</p>\n<div class=\"code-example\"><div class=\"example-header\"><span class=\"language-name\">js</span></div><pre class=\"brush: js notranslate\"><code>const renderBundleEncoder = device.createRenderBundleEncoder({\n  colorFormats: [presentationFormat],\n});\nrecordRenderPass(renderBundleEncoder);\nconst renderBundle = renderBundleEncoder.finish();\n</code></pre></div>\n<p><a href=\"/en-US/docs/Web/API/GPURenderPassEncoder/executeBundles\"><code>GPURenderPassEncoder.executeBundles()</code></a> is then used to reuse the work across multiple render passes to improve performance. Study the example code listing for the full context.</p>\n<div class=\"code-example\"><div class=\"example-header\"><span class=\"language-name\">js</span></div><pre class=\"brush: js notranslate\"><code>// ...\n\nreturn function doDraw(timestamp) {\n  if (startTime === undefined) {\n    startTime = timestamp;\n  }\n  uniformTime[0] = (timestamp - startTime) / 1000;\n  device.queue.writeBuffer(uniformBuffer, timeOffset, uniformTime.buffer);\n\n  renderPassDescriptor.colorAttachments[0].view = context\n    .getCurrentTexture()\n    .createView();\n\n  const commandEncoder = device.createCommandEncoder();\n  const passEncoder = commandEncoder.beginRenderPass(renderPassDescriptor);\n\n  if (settings.renderBundles) {\n    passEncoder.executeBundles([renderBundle]);\n  } else {\n    recordRenderPass(passEncoder);\n  }\n\n  passEncoder.end();\n  device.queue.submit([commandEncoder.finish()]);\n};\n\n// ...\n</code></pre></div>"}},{"type":"specifications","value":{"title":"Specifications","id":"specifications","isH3":false,"specifications":[{"bcdSpecificationURL":"https://gpuweb.github.io/gpuweb/#gpurenderbundle","title":"WebGPU"}],"query":"api.GPURenderBundle"}},{"type":"browser_compatibility","value":{"title":"Browser compatibility","id":"browser_compatibility","isH3":false,"query":"api.GPURenderBundle"}},{"type":"prose","value":{"id":"see_also","title":"See also","isH3":false,"content":"<ul>\n  <li>The <a href=\"/en-US/docs/Web/API/WebGPU_API\">WebGPU API</a></li>\n</ul>"}}],"toc":[{"text":"Instance properties","id":"instance_properties"},{"text":"Examples","id":"examples"},{"text":"Specifications","id":"specifications"},{"text":"Browser compatibility","id":"browser_compatibility"},{"text":"See also","id":"see_also"}],"summary":"The GPURenderBundle interface of the WebGPU API represents a container for pre-recorded bundles of commands.","popularity":0.0009,"modified":null,"other_translations":[],"pageType":"web-api-interface","source":{"folder":"en-us/web/api/gpurenderbundle","github_url":"https://github.com/mdn/content/blob/main/files/en-us/web/api/gpurenderbundle/index.md","last_commit_url":"https://github.com/mdn/content/commit/null","filename":"index.md"},"short_title":"GPURenderBundle","parents":[{"uri":"/en-US/docs/Web","title":"References"},{"uri":"/en-US/docs/Web/API","title":"Web APIs"},{"uri":"/en-US/docs/Web/API/GPURenderBundle","title":"GPURenderBundle"}],"pageTitle":"GPURenderBundle - Web APIs | MDN","noIndexing":false},"url":"/en-US/docs/Web/API/GPURenderBundle"}