{"isMarkdown":true,"isTranslated":false,"isActive":true,"flaws":{},"title":"MediaSourceHandle","mdn_url":"/en-US/docs/Web/API/MediaSourceHandle","locale":"en-US","native":"English (US)","browserCompat":["api.MediaSourceHandle"],"summary":"The MediaSourceHandle interface of the Media Source Extensions API is a proxy for a MediaSource that can be transferred from a dedicated worker back to the main thread and attached to a media element via its HTMLMediaElement.srcObject property. MediaSource objects are not transferable because they are event targets, hence the need for MediaSourceHandles.","popularity":0.0007,"modified":null,"other_translations":[],"pageType":"web-api-interface","source":{"folder":"en-us/web/api/mediasourcehandle","github_url":"https://github.com/mdn/content/blob/main/files/en-us/web/api/mediasourcehandle/index.md","last_commit_url":"https://github.com/mdn/content/commit/null","filename":"index.md"},"short_title":"MediaSourceHandle","parents":[{"uri":"/en-US/docs/Web","title":"References"},{"uri":"/en-US/docs/Web/API","title":"Web APIs"},{"uri":"/en-US/docs/Web/API/MediaSourceHandle","title":"MediaSourceHandle"}],"pageTitle":"MediaSourceHandle - Web APIs | MDN","noIndexing":false,"hash":"ec133a65949e5e3b1da42a2ce0e220e68e39e59ec36b588d0b8548d1e6ec6749"}