{"isMarkdown":true,"isTranslated":false,"isActive":true,"flaws":{},"title":"DocumentPictureInPicture","mdn_url":"/en-US/docs/Web/API/DocumentPictureInPicture","locale":"en-US","native":"English (US)","browserCompat":["api.DocumentPictureInPicture"],"baseline":{"baseline":false,"support":{"chrome":"130","edge":"130"}},"summary":"The DocumentPictureInPicture interface of the Document Picture-in-Picture API is the entry point for creating and handling document picture-in-picture windows.","popularity":0.0018,"modified":null,"other_translations":[],"pageType":"web-api-interface","source":{"folder":"en-us/web/api/documentpictureinpicture","github_url":"https://github.com/mdn/content/blob/main/files/en-us/web/api/documentpictureinpicture/index.md","last_commit_url":"https://github.com/mdn/content/commit/null","filename":"index.md"},"short_title":"DocumentPictureInPicture","parents":[{"uri":"/en-US/docs/Web","title":"References"},{"uri":"/en-US/docs/Web/API","title":"Web APIs"},{"uri":"/en-US/docs/Web/API/DocumentPictureInPicture","title":"DocumentPictureInPicture"}],"pageTitle":"DocumentPictureInPicture - Web APIs | MDN","noIndexing":false,"hash":"20cd92c74bcbda66816dc64fb9438b05631962ff77d5de78b6d3e9623b431e87"}