{"isMarkdown":true,"isTranslated":false,"isActive":true,"flaws":{},"title":"BluetoothRemoteGATTServer","mdn_url":"/en-US/docs/Web/API/BluetoothRemoteGATTServer","locale":"en-US","native":"English (US)","browserCompat":["api.BluetoothRemoteGATTServer"],"baseline":{"baseline":false,"support":{"chrome":"70","chrome_android":"56","edge":"79"}},"summary":"The BluetoothRemoteGATTServer interface of the Web Bluetooth API represents a GATT\n  Server on a remote device.","popularity":0.0019,"modified":"2020-10-15T21:38:20.930Z","other_translations":[],"pageType":"web-api-interface","source":{"folder":"en-us/web/api/bluetoothremotegattserver","github_url":"https://github.com/mdn/content/blob/main/files/en-us/web/api/bluetoothremotegattserver/index.md","last_commit_url":"https://github.com/mdn/content/commit/null","filename":"index.md"},"short_title":"BluetoothRemoteGATTServer","parents":[{"uri":"/en-US/docs/Web","title":"References"},{"uri":"/en-US/docs/Web/API","title":"Web APIs"},{"uri":"/en-US/docs/Web/API/BluetoothRemoteGATTServer","title":"BluetoothRemoteGATTServer"}],"pageTitle":"BluetoothRemoteGATTServer - Web APIs | MDN","noIndexing":false,"hash":"51092d4efc488857303a45f490ec22f8a94c4d0856b1cc0b5f2487d3460a9b97"}